cvzoomwindow/__init__.py
cvzoomwindow/affine.py
cvzoomwindow-0.0.3.dist-info/METADATA
cvzoomwindow-0.0.3.dist-info/WHEEL
cvzoomwindow-0.0.3.dist-info/top_level.txt
cvzoomwindow-0.0.3.dist-info/RECORD
