Metadata-Version: 2.1
Name: cvzoomwindow
Version: 0.0.3
Summary: CvNameWindow class that adds zoom and pan functions to OpenCV's namedWindow
Home-page: https://imagingsolution.net/program/python/opencv-python/cvzoomwindow_class/
Author: ImaginSolution
Author-email: 
License: MIT
Keywords: OpenCV namedWindow zoom pan
Classifier: License :: OSI Approved :: MIT License
Classifier: Natural Language :: Japanese
Classifier: Operating System :: Microsoft :: Windows :: Windows 10
Classifier: Operating System :: Microsoft :: Windows :: Windows 11
Classifier: Programming Language :: Python :: 3.8
